pip_gui/__init__.py
pip_gui/consoleOutput.py
pip_gui/mainGUI.py
pip_gui/GUI/__init__.py
pip_gui/GUI/installScreen.py
pip_gui/GUI/progressScreen.py
pip_gui/GUI/startScreen.py
pip_gui/GUI/uninstallScreen.py
pip_gui/GUI/updateScreen.py
pip_gui/Package_Management/__init__.py
pip_gui/Package_Management/installedList.py
pip_gui/Package_Management/outdatedList.py
pip_gui/Scraping/__init__.py
pip_gui/Scraping/genreList.py
pip_gui/Scraping/githubFile.py
pip_gui/Scraping/packageList.py
pip_gui/Scraping/pypiList.py
pip_gui-1.1.dist-info/DESCRIPTION.rst
pip_gui-1.1.dist-info/METADATA
pip_gui-1.1.dist-info/RECORD
pip_gui-1.1.dist-info/WHEEL
pip_gui-1.1.dist-info/entry_points.txt
pip_gui-1.1.dist-info/metadata.json
pip_gui-1.1.dist-info/top_level.txt
