Metadata-Version: 2.0
Name: pip-gui
Version: 1.1
Summary: UNKNOWN
Home-page: https://github.com/GDGVIT/pip-gui
Author: GDGVIT
Author-email: UNKNOWN
License: UNKNOWN
Platform: UNKNOWN
Classifier: Development Status :: 4 - Beta
Classifier: License :: OSI Approved :: Apache Software License
Classifier: Environment :: X11 Applications :: Qt
Classifier: Programming Language :: Python :: 2
Classifier: Programming Language :: Python :: 2 :: Only
Classifier: Programming Language :: Python :: 2.7
Classifier: Programming Language :: Python :: Implementation :: CPython
Requires-Dist: beautifulsoup4 (<4.5.4,>=4.5)
